canaro/__init__.py
canaro/_meta.py
canaro/model.py
canaro/tools.py
canaro/train.py
canaro/generators/__init__.py
canaro/generators/imagedatagen.py
canaro/models/LeNet.py
canaro/models/VGG16.py
canaro/models/__init__.py
canaro/models/default_model.py
canaro/models/simpsons.py
canaro/utils/__init__.py
canaro/utils/categorical.py
canaro/utils/h5_to_pb.py
canaro-1.1.0.dist-info/AUTHORS
canaro-1.1.0.dist-info/LICENSE
canaro-1.1.0.dist-info/METADATA
canaro-1.1.0.dist-info/WHEEL
canaro-1.1.0.dist-info/top_level.txt
canaro-1.1.0.dist-info/RECORD
