Metadata-Version: 2.1
Name: canaro
Version: 1.1.0
Summary: A Python library including support for Deep Learning models built using the Keras framework.
Home-page: https://github.com/jasmcaus/canaro
Author: Jason Dsouza
Author-email: jasmcaus@gmail.com
Maintainer: Jason Dsouza
License: MIT
Download-URL: https://pypi.org/project/canaro/
Project-URL: Bug Tracker, https://github.com/jasmcaus/canaro/issues
Project-URL: Documentation, https://github.com/jasmcaus/canaro/blob/master/DOCS.md
Project-URL: Source Code, https://github.com/jasmcaus/canaro
Keywords: computer vision,deep learning,tensorflow,keras,convolutional neural networks,opencv,matplotlib
Platform: UNKNOWN
Classifier: Development Status :: 3 - Alpha
Classifier: Intended Audience :: Developers
Classifier: Intended Audience :: Education
Classifier: Intended Audience :: Science/Research
Classifier: Programming Language :: Python :: 3
Classifier: Programming Language :: Python :: 3 :: Only
Classifier: Programming Language :: Python :: 3.5
Classifier: Programming Language :: Python :: 3.6
Classifier: Programming Language :: Python :: 3.7
Classifier: Programming Language :: Python :: 3.8
Classifier: Operating System :: MacOS :: MacOS X
Classifier: Operating System :: Microsoft :: Windows
Classifier: License :: OSI Approved :: MIT License
Requires-Dist: tensorflow
Requires-Dist: caer
Provides-Extra: caer
Requires-Dist: caer ; extra == 'caer'
